{
  "ruler": {
    "start": 1762341821078,
    "@context": {
      "TemporalRuler": "https://emissor.org#TemporalRuler",
      "id": "@id",
      "start": "https://emissor.org#start",
      "end": "https://emissor.org#end",
      "container_id": {
        "@id": "https://emissor.org#container_id",
        "@type": "@id"
      }
    },
    "@type": "TemporalRuler",
    "container_id": "1731fe63-4fe1-4951-adf8-c918f91e977b",
    "end": null,
    "_py_type": "emissor.representation.container-TemporalRuler"
  },
  "id": "1731fe63-4fe1-4951-adf8-c918f91e977b",
  "@context": {
    "Scenario": "https://emissor.org#Scenario",
    "id": "@id",
    "context": "https://emissor.org#context",
    "signals": "https://emissor.org#signals",
    "ruler": "https://emissor.org#ruler"
  },
  "@type": "Scenario",
  "context": {
    "speaker": {
      "uri": "http://cltl.nl/leolani/world/human_speaker",
      "name": "Human"
    },
    "agent": {
      "uri": "http://cltl.nl/leolani/world/leolani",
      "name": "Leolani"
    },
    "location": "{'ip': '79.225.179.168', 'hostname': 'p4fe1b3a8.dip0.t-ipconnect.de', 'city': 'Berlin', 'region': 'State of Berlin', 'country': 'DE', 'loc': '52.5244,13.4105', 'org': 'AS3320 Deutsche Telekom AG', 'postal': '10119', 'timezone': 'Europe/Berlin', 'readme': 'https://ipinfo.io/missingauth'}",
    "@context": {
      "ScenarioContext": "https://emissor.org#ScenarioContext",
      "id": "@id",
      "agent": "https://emissor.org#agent"
    },
    "persons": [],
    "@type": "ScenarioContext",
    "objects": [],
    "location_id": "da5cc837-4d90-4a26-bc2d-28e85297a891",
    "_py_type": "cltl.combot.event.emissor-LeolaniContext"
  },
  "signals": {
    "text": "./text.json"
  }
}